ffmpeg_media_type/__init__.py
ffmpeg_media_type/cache/3dostr.json
ffmpeg_media_type/cache/3g2.json
ffmpeg_media_type/cache/3gp.json
ffmpeg_media_type/cache/4xm.json
ffmpeg_media_type/cache/a64.json
ffmpeg_media_type/cache/aa.json
ffmpeg_media_type/cache/aac.json
ffmpeg_media_type/cache/aax.json
ffmpeg_media_type/cache/ac3.json
ffmpeg_media_type/cache/ac4.json
ffmpeg_media_type/cache/ace.json
ffmpeg_media_type/cache/acm.json
ffmpeg_media_type/cache/act.json
ffmpeg_media_type/cache/adf.json
ffmpeg_media_type/cache/adp.json
ffmpeg_media_type/cache/ads.json
ffmpeg_media_type/cache/adts.json
ffmpeg_media_type/cache/adx.json
ffmpeg_media_type/cache/aea.json
ffmpeg_media_type/cache/afc.json
ffmpeg_media_type/cache/aiff.json
ffmpeg_media_type/cache/aix.json
ffmpeg_media_type/cache/alaw.json
ffmpeg_media_type/cache/alias_pix.json
ffmpeg_media_type/cache/alp.json
ffmpeg_media_type/cache/amr.json
ffmpeg_media_type/cache/amrnb.json
ffmpeg_media_type/cache/amrwb.json
ffmpeg_media_type/cache/amv.json
ffmpeg_media_type/cache/anm.json
ffmpeg_media_type/cache/apac.json
ffmpeg_media_type/cache/apc.json
ffmpeg_media_type/cache/ape.json
ffmpeg_media_type/cache/apm.json
ffmpeg_media_type/cache/apng.json
ffmpeg_media_type/cache/aptx.json
ffmpeg_media_type/cache/aptx_hd.json
ffmpeg_media_type/cache/aqtitle.json
ffmpeg_media_type/cache/argo_asf.json
ffmpeg_media_type/cache/argo_brp.json
ffmpeg_media_type/cache/argo_cvg.json
ffmpeg_media_type/cache/asf.json
ffmpeg_media_type/cache/asf_o.json
ffmpeg_media_type/cache/asf_stream.json
ffmpeg_media_type/cache/ass.json
ffmpeg_media_type/cache/ast.json
ffmpeg_media_type/cache/au.json
ffmpeg_media_type/cache/audiotoolbox.json
ffmpeg_media_type/cache/av1.json
ffmpeg_media_type/cache/avfoundation.json
ffmpeg_media_type/cache/avi.json
ffmpeg_media_type/cache/avif.json
ffmpeg_media_type/cache/avm2.json
ffmpeg_media_type/cache/avr.json
ffmpeg_media_type/cache/avs.json
ffmpeg_media_type/cache/avs2.json
ffmpeg_media_type/cache/avs3.json
ffmpeg_media_type-1.0.5.dist-info/LICENSE
ffmpeg_media_type-1.0.5.dist-info/METADATA
ffmpeg_media_type-1.0.5.dist-info/WHEEL
ffmpeg_media_type-1.0.5.dist-info/entry_points.txt
ffmpeg_media_type-1.0.5.dist-info/RECORD
