Metadata-Version: 2.1
Name: ffmpeg-media-type
Version: 1.0.5
Summary: ffmpeg-media-type is a Python library that utilizes FFmpeg to extract crucial details from media files, such as duration, width, and height. With seamless integration of 100% typehint support, it offers a user-friendly interface for easy access to media file information.
Keywords: ffmpeg,ffprobe,video,image,audio,media,mimetype,mp4,mp3,mov,webm
Author: lucemia
Author-email: lucemia@gmail.com
Requires-Python: >=3.10,<4.0
Classifier: Intended Audience :: Developers
Classifier: License :: OSI Approved :: MIT License
Classifier: Natural Language :: English
Classifier: Operating System :: OS Independent
Classifier: Programming Language :: Python
Classifier: Programming Language :: Python :: 3
Classifier: Programming Language :: Python :: 3.10
Classifier: Programming Language :: Python :: 3.11
Classifier: Programming Language :: Python :: 3.12
